music_search/__init__.py
music_search-1.0.0.dist-info/METADATA
music_search-1.0.0.dist-info/WHEEL
music_search-1.0.0.dist-info/entry_points.txt
music_search-1.0.0.dist-info/top_level.txt
music_search-1.0.0.dist-info/RECORD
